[
  {
    "ts": 1774383462490,
    "perfTs": 640.7999999523163,
    "eventTs": 624.1999999880791,
    "kind": "interaction",
    "eventName": "click",
    "uid": "mainTabs",
    "traceId": "i-mn523m1m-8ocwm4",
    "componentType": "Tabs",
    "componentLabel": "Main tabs",
    "interaction": "click",
    "ariaRole": "tab",
    "ariaName": "Settings",
    "detail": {
      "componentId": "mainTabs",
      "targetTag": "DIV",
      "selectorPath": "[data-testid=\"mainTabs\"] >> text=Settings",
      "text": "UsersSettingsAboutSettingsShow email column:Items per page:Notes:",
      "ariaRole": "tab",
      "ariaName": "Settings",
      "button": 0
    },
    "text": "{\n  \"componentId\": \"mainTabs\",\n  \"targetTag\": \"DIV\",\n  \"selectorPath\": \"[data-testid=\\\"mainTabs\\\"] >> text=Settings\",\n  \"text\": \"UsersSettingsAboutSettingsShow email column:Items per page:Notes:\",\n  \"ariaRole\": \"tab\",\n  \"ariaName\": \"Settings\",\n  \"button\": 0\n}"
  },
  {
    "ts": 1774383462527,
    "perfTs": 677.6999999880791,
    "traceId": "i-mn523m1m-8ocwm4",
    "kind": "focus:change",
    "component": "Tabs",
    "displayLabel": "About",
    "tabIndex": 2,
    "tabId": ":rj:",
    "tabLabel": "About"
  },
  {
    "ts": 1774383462530,
    "perfTs": 681.3999999761581,
    "eventTs": 676.8999999761581,
    "kind": "interaction",
    "eventName": "click",
    "uid": "mainTabs",
    "traceId": "i-mn523m2q-o0tary",
    "componentType": "Tabs",
    "componentLabel": "Main tabs",
    "interaction": "click",
    "ariaRole": "tab",
    "ariaName": "About",
    "detail": {
      "componentId": "mainTabs",
      "targetTag": "DIV",
      "selectorPath": "[data-testid=\"mainTabs\"] >> text=About",
      "text": "UsersSettingsAboutAboutXMLUI Regression Test App — exercises core components …",
      "ariaRole": "tab",
      "ariaName": "About",
      "button": 0
    },
    "text": "{\n  \"componentId\": \"mainTabs\",\n  \"targetTag\": \"DIV\",\n  \"selectorPath\": \"[data-testid=\\\"mainTabs\\\"] >> text=About\",\n  \"text\": \"UsersSettingsAboutAboutXMLUI Regression Test App — exercises core components …\",\n  \"ariaRole\": \"tab\",\n  \"ariaName\": \"About\",\n  \"button\": 0\n}"
  },
  {
    "ts": 1774383462764,
    "perfTs": 914.8999999761581,
    "traceId": "startup-mn523luu",
    "kind": "api:complete",
    "url": "/api/users",
    "method": "GET",
    "instanceId": "ds-02jbke-mn523lvu",
    "result": [
      {
        "id": 1,
        "name": "Leanne Graham",
        "email": "Sincere@april.biz",
        "phone": "1-770-736-8031"
      },
      {
        "id": 2,
        "name": "Ervin Howell",
        "email": "Shanna@melissa.tv",
        "phone": "010-692-6593"
      }
    ]
  },
  {
    "ts": 1774383462765,
    "perfTs": 916.1999999880791,
    "traceId": "startup-mn523luu",
    "instanceId": "ds-02jbke-mn523lvu",
    "dataSourceUrl": "/api/users",
    "ownerUid": "users",
    "ownerFileId": "http://localhost:8000/Main.xmlui",
    "ownerSource": {
      "start": 137,
      "end": 183
    },
    "text": "[\n  \"state:changes\",\n  {\n    \"uid\": \"users\",\n    \"eventName\": \"DataSource:users\",\n    \"instanceId\": \"ds-02jbke-mn523lvu\",\n    \"diff\": [\n      {\n        \"path\": \"DataSource:users\",\n        \"type\": \"update\",\n        \"after\": [\n          {\n            \"id\": 1,\n            \"name\": \"Leanne Graham\",\n            \"email\": \"Sincere@april.biz\",\n            \"phone\": \"1-770-736-8031\"\n          },\n          {\n            \"id\": 2,\n            \"name\": \"Ervin Howell\",\n            \"email\": \"Shanna@melissa.tv\",\n            \"phone\": \"010-692-6593\"\n          }\n        ],\n        \"beforeJson\": \"undefined\",\n        \"afterJson\": \"[\\n  {\\n    \\\"id\\\": 1,\\n    \\\"name\\\": \\\"Leanne Graham\\\",\\n    \\\"email\\\": \\\"Sincere@april.biz\\\",\\n    \\\"phone\\\": \\\"1-770-736-8031\\\"\\n  },\\n  {\\n    \\\"id\\\": 2,\\n    \\\"name\\\": \\\"Ervin Howell\\\",\\n    \\\"email\\\": \\\"Shanna@melissa.tv\\\",\\n    \\\"phone\\\": \\\"010-692-6593\\\"\\n  }\\n]\",\n        \"diffText\": \"path: DataSource:users\\n- undefined\\n+ [\\n  {\\n    \\\"id\\\": 1,\\n    \\\"name\\\": \\\"Leanne Graham\\\",\\n    \\\"email\\\": \\\"Sincere@april.biz\\\",\\n    \\\"phone\\\": \\\"1-770-736-8031\\\"\\n  },\\n  {\\n    \\\"id\\\": 2,\\n    \\\"name\\\": \\\"Ervin Howell\\\",\\n    \\\"email\\\": \\\"Shanna@melissa.tv\\\",\\n    \\\"phone\\\": \\\"010-692-6593\\\"\\n  }\\n]\",\n        \"diffPretty\": \"path: DataSource:users\\n- undefined\\n+ [\\n+   {\\n+     \\\"id\\\": 1,\\n+     \\\"name\\\": \\\"Leanne Graham\\\",\\n+     \\\"email\\\": \\\"Sincere@april.biz\\\",\\n+     \\\"phone\\\": \\\"1-770-736-8031\\\"\\n+   },\\n+   {\\n+     \\\"id\\\": 2,\\n+     \\\"name\\\": \\\"Ervin Howell\\\",\\n+     \\\"email\\\": \\\"Shanna@melissa.tv\\\",\\n+     \\\"phone\\\": \\\"010-692-6593\\\"\\n+   }\\n+ ]\"\n      }\n    ]\n  }\n]",
    "kind": "state:changes",
    "eventName": "DataSource:users",
    "uid": "users",
    "componentType": "DataSource",
    "diffPretty": "path: DataSource:users\n- undefined\n+ [\n+   {\n+     \"id\": 1,\n+     \"name\": \"Leanne Graham\",\n+     \"email\": \"Sincere@april.biz\",\n+     \"phone\": \"1-770-736-8031\"\n+   },\n+   {\n+     \"id\": 2,\n+     \"name\": \"Ervin Howell\",\n+     \"email\": \"Shanna@melissa.tv\",\n+     \"phone\": \"010-692-6593\"\n+   }\n+ ]",
    "diffJson": [
      {
        "path": "DataSource:users",
        "type": "update",
        "after": [
          {
            "id": 1,
            "name": "Leanne Graham",
            "email": "Sincere@april.biz",
            "phone": "1-770-736-8031"
          },
          {
            "id": 2,
            "name": "Ervin Howell",
            "email": "Shanna@melissa.tv",
            "phone": "010-692-6593"
          }
        ],
        "beforeJson": "undefined",
        "afterJson": "[\n  {\n    \"id\": 1,\n    \"name\": \"Leanne Graham\",\n    \"email\": \"Sincere@april.biz\",\n    \"phone\": \"1-770-736-8031\"\n  },\n  {\n    \"id\": 2,\n    \"name\": \"Ervin Howell\",\n    \"email\": \"Shanna@melissa.tv\",\n    \"phone\": \"010-692-6593\"\n  }\n]",
        "diffText": "path: DataSource:users\n- undefined\n+ [\n  {\n    \"id\": 1,\n    \"name\": \"Leanne Graham\",\n    \"email\": \"Sincere@april.biz\",\n    \"phone\": \"1-770-736-8031\"\n  },\n  {\n    \"id\": 2,\n    \"name\": \"Ervin Howell\",\n    \"email\": \"Shanna@melissa.tv\",\n    \"phone\": \"010-692-6593\"\n  }\n]",
        "diffPretty": "path: DataSource:users\n- undefined\n+ [\n+   {\n+     \"id\": 1,\n+     \"name\": \"Leanne Graham\",\n+     \"email\": \"Sincere@april.biz\",\n+     \"phone\": \"1-770-736-8031\"\n+   },\n+   {\n+     \"id\": 2,\n+     \"name\": \"Ervin Howell\",\n+     \"email\": \"Shanna@melissa.tv\",\n+     \"phone\": \"010-692-6593\"\n+   }\n+ ]"
      }
    ]
  }
]